pylnlst/__init__.py
pylnlst/main.py
pylnlst-0.2.0.dist-info/METADATA
pylnlst-0.2.0.dist-info/WHEEL
pylnlst-0.2.0.dist-info/entry_points.txt
pylnlst-0.2.0.dist-info/licenses/LICENSE
pylnlst-0.2.0.dist-info/RECORD
