Metadata-Version: 2.3
Name: pylnlst
Version: 0.2.0
Summary: CLI tool to automate the creation of symbolic links in a destination directory.
Project-URL: Repository, https://github.com/sergiofgonzalez/pylnlst
Author-email: "Sergio F. Gonzalez" <sergio.f.gonzalez@gmail.com>
License: MIT
Requires-Python: >=3.12
Requires-Dist: typer>=0.14.0
